random_colors/__init__.py
random_colors/main.py
random_colors-0.1.0.dist-info/WHEEL
random_colors-0.1.0.dist-info/METADATA
random_colors-0.1.0.dist-info/RECORD
